PyAres/__init__.py
PyAres/Analyzing/__init__.py
PyAres/Analyzing/analysis_service.py
PyAres/Analyzing/analyzer_models.py
PyAres/Demo/analyzer_test.py
PyAres/Demo/analyzer_test_tools_demo.py
PyAres/Demo/analyzer_wiki.py
PyAres/Demo/device_test.py
PyAres/Demo/hotplate.py
PyAres/Demo/planner_test.py
PyAres/Demo/planner_test_tools_demo.py
PyAres/Demo/planner_wiki.py
PyAres/Demo/rotary_mixer.py
PyAres/Device/__init__.py
PyAres/Device/device_models.py
PyAres/Device/device_service.py
PyAres/Device/device_warnings.py
PyAres/Models/__init__.py
PyAres/Models/ares_data_models.py
PyAres/Planning/__init__.py
PyAres/Planning/planner_models.py
PyAres/Planning/planning_service.py
PyAres/Utils/ares_data_schema_utils.py
PyAres/Utils/ares_data_type_utils.py
PyAres/Utils/ares_device_command_utils.py
PyAres/Utils/ares_outcome_utils.py
PyAres/Utils/ares_struct_utils.py
PyAres/Utils/ares_value_utils.py
PyAres/Utils/param_history_info_utils.py
PyAres/Utils/plan_request_utils.py
PyAres/Utils/plan_response_utils.py
PyAres/Utils/planning_param_utils.py
PyAres/test_tools/__init__.py
PyAres/test_tools/analyzer_tester.py
PyAres/test_tools/planner_tester.py
pyares-0.3.3.dist-info/METADATA
pyares-0.3.3.dist-info/WHEEL
pyares-0.3.3.dist-info/licenses/LICENSE
pyares-0.3.3.dist-info/RECORD
