Metadata-Version: 2.4
Name: PyAres
Version: 0.3.3
Summary: The official Python library for ARES.
Project-URL: Homepage, https://github.com/AFRL-ARES/PyAres
Author-email: AFRL <AFRL.RX.AREScontact@us.af.mil>
License: MIT
License-File: LICENSE
Classifier: Operating System :: OS Independent
Classifier: Programming Language :: Python :: 3
Requires-Python: >=3.10
Requires-Dist: ares-datamodel>=0.16.1
Requires-Dist: grpcio-tools>=1.75.1
Requires-Dist: grpcio<2.0.0,>=1.71.0
